lyrebird_api_coverage/__init__.py
lyrebird_api_coverage/app_ui.py
lyrebird_api_coverage/client/__init__.py
lyrebird_api_coverage/client/config.py
lyrebird_api_coverage/client/context.py
lyrebird_api_coverage/client/event_subscibe.py
lyrebird_api_coverage/client/filter_url.py
lyrebird_api_coverage/client/format_url.py
lyrebird_api_coverage/client/jsonscheme.py
lyrebird_api_coverage/client/load_base.py
lyrebird_api_coverage/client/merge_algorithm.py
lyrebird_api_coverage/client/report.py
lyrebird_api_coverage/client/url_compare.py
lyrebird_api_coverage/default_conf/base.json
lyrebird_api_coverage/default_conf/conf.json
lyrebird_api_coverage/default_conf/filter_config.json
lyrebird_api_coverage/handlers/__init__.py
lyrebird_api_coverage/handlers/base_source_handler.py
lyrebird_api_coverage/handlers/filter_handler.py
lyrebird_api_coverage/handlers/import_file_handler.py
lyrebird_api_coverage/handlers/result_handler.py
lyrebird_api_coverage/proxy/__init__.py
lyrebird_api_coverage/proxy/proxy_handler.py
lyrebird_api_coverage/static/component/api-list.vue
lyrebird_api_coverage/static/component/banner.vue
lyrebird_api_coverage/static/component/coverage.vue
lyrebird_api_coverage/static/component/info.vue
lyrebird_api_coverage/static/component/main.vue
lyrebird_api_coverage/static/js/main.js
lyrebird_api_coverage/templates/index.html
lyrebird_api_coverage-0.2.1.dist-info/METADATA
lyrebird_api_coverage-0.2.1.dist-info/RECORD
lyrebird_api_coverage-0.2.1.dist-info/WHEEL
lyrebird_api_coverage-0.2.1.dist-info/entry_points.txt
lyrebird_api_coverage-0.2.1.dist-info/top_level.txt
